operatorsMelissa/__init__.py
operatorsMelissa/add.py
operatorsMelissa/subtract.py
operatorsMelissa-0.0.1.dist-info/LICENSE
operatorsMelissa-0.0.1.dist-info/METADATA
operatorsMelissa-0.0.1.dist-info/WHEEL
operatorsMelissa-0.0.1.dist-info/top_level.txt
operatorsMelissa-0.0.1.dist-info/RECORD
