Metadata-Version: 2.1
Name: operatorsMelissa
Version: 0.0.1
Summary: Meu primeiro pacote
Author: Melissa
Author-email: msnmelissaoa15@hotmail.com
Classifier: Development Status :: 3 - Alpha
Classifier: Intended Audience :: Education
Classifier: Programming Language :: Python :: 3
Classifier: Operating System :: OS Independent
License-File: LICENSE
